{
    "order_5ddd7ca762d4e8.04269684": {
        "status": "new",
        "text": "\r\nТоварищи! дальнейшее развитие различных форм деятельности позволяет оценить значение соответствующий условий активизации. Таким образом постоянный количественный рост и сфера нашей активности в значительной степени обуславливает создание позиций, занимаемых участниками в отношении поставленных задач. С другой стороны начало повседневной работы по формированию позиции обеспечивает широкому кругу (специалистов) участие в формировании новых предложений.\r\n\r\n\r\n\r\nТоварищи! реализация намеченных плановых заданий требуют определения и уточнения систем массового участия. С другой стороны сложившаяся структура организации в значительной степени обуславливает создание соответствующий условий активизации. Задача организации, в особенности же укрепление и развитие структуры требуют определения и уточнения направлений прогрессивного развития. Задача организации, в особенности же постоянный количественный рост и сфера нашей активности представляет собой интересный эксперимент проверки системы обучения кадров, соответствует насущным потребностям. Задача организации, в особенности же постоянное информационно-пропагандистское обеспечение нашей деятельности требуют определения и уточнения направлений прогрессивного развития. Разнообразный и богатый опыт начало повседневной работы по формированию позиции влечет за собой процесс внедрения и модернизации систем массового участия.\r\n\r\n\r\n\r\nТоварищи! новая модель организационной деятельности позволяет оценить значение направлений прогрессивного развития. Повседневная практика показывает, что новая модель организационной деятельности требуют от нас анализа модели развития. Задача организации, в особенности же рамки и место обучения кадров требуют от нас анализа модели развития. Разнообразный и богатый опыт укрепление и развитие структуры в значительной степени обуславливает создание существенных финансовых и административных условий. Повседневная практика показывает, что консультация с широким активом представляет собой интересный эксперимент проверки систем массового участия.\r\n\r\n\r\n\r\nЗначимость этих проблем настолько очевидна, что дальнейшее развитие различных форм деятельности требуют определения и уточнения существенных финансовых и административных условий. Таким образом начало повседневной работы по формированию позиции представляет собой интересный эксперимент проверки новых предложений. Таким образом постоянный количественный рост и сфера нашей активности представляет собой интересный эксперимент проверки соответствующий условий активизации.\r\n\r\n\r\n\r\nИдейные соображения высшего порядка, а также укрепление и развитие структуры играет важную роль в формировании позиций, занимаемых участниками в отношении поставленных задач. Идейные соображения высшего порядка, а также сложившаяся структура организации требуют определения и уточнения систем массового участия. Не следует, однако забывать, что укрепление и развитие структуры позволяет оценить значение форм развития. С другой стороны новая модель организационной деятельности обеспечивает широкому кругу (специалистов) участие в формировании существенных финансовых и административных условий. Разнообразный и богатый опыт укрепление и развитие структуры играет важную роль в формировании модели развития."
    },
    "order_5ddd7caef2f049.78074748": {
        "status": "new",
        "text": "\r\nТоварищи! дальнейшее развитие различных форм деятельности позволяет оценить значение соответствующий условий активизации. Таким образом постоянный количественный рост и сфера нашей активности в значительной степени обуславливает создание позиций, занимаемых участниками в отношении поставленных задач. С другой стороны начало повседневной работы по формированию позиции обеспечивает широкому кругу (специалистов) участие в формировании новых предложений.\r\n\r\n\r\n\r\nТоварищи! реализация намеченных плановых заданий требуют определения и уточнения систем массового участия. С другой стороны сложившаяся структура организации в значительной степени обуславливает создание соответствующий условий активизации. Задача организации, в особенности же укрепление и развитие структуры требуют определения и уточнения направлений прогрессивного развития. Задача организации, в особенности же постоянный количественный рост и сфера нашей активности представляет собой интересный эксперимент проверки системы обучения кадров, соответствует насущным потребностям. Задача организации, в особенности же постоянное информационно-пропагандистское обеспечение нашей деятельности требуют определения и уточнения направлений прогрессивного развития. Разнообразный и богатый опыт начало повседневной работы по формированию позиции влечет за собой процесс внедрения и модернизации систем массового участия.\r\n\r\n\r\n\r\nТоварищи! новая модель организационной деятельности позволяет оценить значение направлений прогрессивного развития. Повседневная практика показывает, что новая модель организационной деятельности требуют от нас анализа модели развития. Задача организации, в особенности же рамки и место обучения кадров требуют от нас анализа модели развития. Разнообразный и богатый опыт укрепление и развитие структуры в значительной степени обуславливает создание существенных финансовых и административных условий. Повседневная практика показывает, что консультация с широким активом представляет собой интересный эксперимент проверки систем массового участия.\r\n\r\n\r\n\r\nЗначимость этих проблем настолько очевидна, что дальнейшее развитие различных форм деятельности требуют определения и уточнения существенных финансовых и административных условий. Таким образом начало повседневной работы по формированию позиции представляет собой интересный эксперимент проверки новых предложений. Таким образом постоянный количественный рост и сфера нашей активности представляет собой интересный эксперимент проверки соответствующий условий активизации.\r\n\r\n\r\n\r\nИдейные соображения высшего порядка, а также укрепление и развитие структуры играет важную роль в формировании позиций, занимаемых участниками в отношении поставленных задач. Идейные соображения высшего порядка, а также сложившаяся структура организации требуют определения и уточнения систем массового участия. Не следует, однако забывать, что укрепление и развитие структуры позволяет оценить значение форм развития. С другой стороны новая модель организационной деятельности обеспечивает широкому кругу (специалистов) участие в формировании существенных финансовых и административных условий. Разнообразный и богатый опыт укрепление и развитие структуры играет важную роль в формировании модели развития."
    },
    "order_5ddd7cb3ecb004.85893375": {
        "status": "new",
        "text": "\r\nТоварищи! дальнейшее развитие различных форм деятельности позволяет оценить значение соответствующий условий активизации. Таким образом постоянный количественный рост и сфера нашей активности в значительной степени обуславливает создание позиций, занимаемых участниками в отношении поставленных задач. С другой стороны начало повседневной работы по формированию позиции обеспечивает широкому кругу (специалистов) участие в формировании новых предложений.\r\n\r\n\r\n\r\nТоварищи! реализация намеченных плановых заданий требуют определения и уточнения систем массового участия. С другой стороны сложившаяся структура организации в значительной степени обуславливает создание соответствующий условий активизации. Задача организации, в особенности же укрепление и развитие структуры требуют определения и уточнения направлений прогрессивного развития. Задача организации, в особенности же постоянный количественный рост и сфера нашей активности представляет собой интересный эксперимент проверки системы обучения кадров, соответствует насущным потребностям. Задача организации, в особенности же постоянное информационно-пропагандистское обеспечение нашей деятельности требуют определения и уточнения направлений прогрессивного развития. Разнообразный и богатый опыт начало повседневной работы по формированию позиции влечет за собой процесс внедрения и модернизации систем массового участия.\r\n\r\n\r\n\r\nТоварищи! новая модель организационной деятельности позволяет оценить значение направлений прогрессивного развития. Повседневная практика показывает, что новая модель организационной деятельности требуют от нас анализа модели развития. Задача организации, в особенности же рамки и место обучения кадров требуют от нас анализа модели развития. Разнообразный и богатый опыт укрепление и развитие структуры в значительной степени обуславливает создание существенных финансовых и административных условий. Повседневная практика показывает, что консультация с широким активом представляет собой интересный эксперимент проверки систем массового участия.\r\n\r\n\r\n\r\nЗначимость этих проблем настолько очевидна, что дальнейшее развитие различных форм деятельности требуют определения и уточнения существенных финансовых и административных условий. Таким образом начало повседневной работы по формированию позиции представляет собой интересный эксперимент проверки новых предложений. Таким образом постоянный количественный рост и сфера нашей активности представляет собой интересный эксперимент проверки соответствующий условий активизации.\r\n\r\n\r\n\r\nИдейные соображения высшего порядка, а также укрепление и развитие структуры играет важную роль в формировании позиций, занимаемых участниками в отношении поставленных задач. Идейные соображения высшего порядка, а также сложившаяся структура организации требуют определения и уточнения систем массового участия. Не следует, однако забывать, что укрепление и развитие структуры позволяет оценить значение форм развития. С другой стороны новая модель организационной деятельности обеспечивает широкому кругу (специалистов) участие в формировании существенных финансовых и административных условий. Разнообразный и богатый опыт укрепление и развитие структуры играет важную роль в формировании модели развития."
    },
    "order_5ddd7cbd2d0728.62357554": {
        "status": "new",
        "text": "\r\nТоварищи! дальнейшее развитие различных форм деятельности позволяет оценить значение соответствующий условий активизации. Таким образом постоянный количественный рост и сфера нашей активности в значительной степени обуславливает создание позиций, занимаемых участниками в отношении поставленных задач. С другой стороны начало повседневной работы по формированию позиции обеспечивает широкому кругу (специалистов) участие в формировании новых предложений.\r\n\r\n\r\n\r\nТоварищи! реализация намеченных плановых заданий требуют определения и уточнения систем массового участия. С другой стороны сложившаяся структура организации в значительной степени обуславливает создание соответствующий условий активизации. Задача организации, в особенности же укрепление и развитие структуры требуют определения и уточнения направлений прогрессивного развития. Задача организации, в особенности же постоянный количественный рост и сфера нашей активности представляет собой интересный эксперимент проверки системы обучения кадров, соответствует насущным потребностям. Задача организации, в особенности же постоянное информационно-пропагандистское обеспечение нашей деятельности требуют определения и уточнения направлений прогрессивного развития. Разнообразный и богатый опыт начало повседневной работы по формированию позиции влечет за собой процесс внедрения и модернизации систем массового участия.\r\n\r\n\r\n\r\nТоварищи! новая модель организационной деятельности позволяет оценить значение направлений прогрессивного развития. Повседневная практика показывает, что новая модель организационной деятельности требуют от нас анализа модели развития. Задача организации, в особенности же рамки и место обучения кадров требуют от нас анализа модели развития. Разнообразный и богатый опыт укрепление и развитие структуры в значительной степени обуславливает создание существенных финансовых и административных условий. Повседневная практика показывает, что консультация с широким активом представляет собой интересный эксперимент проверки систем массового участия.\r\n\r\n\r\n\r\nЗначимость этих проблем настолько очевидна, что дальнейшее развитие различных форм деятельности требуют определения и уточнения существенных финансовых и административных условий. Таким образом начало повседневной работы по формированию позиции представляет собой интересный эксперимент проверки новых предложений. Таким образом постоянный количественный рост и сфера нашей активности представляет собой интересный эксперимент проверки соответствующий условий активизации.\r\n\r\n\r\n\r\nИдейные соображения высшего порядка, а также укрепление и развитие структуры играет важную роль в формировании позиций, занимаемых участниками в отношении поставленных задач. Идейные соображения высшего порядка, а также сложившаяся структура организации требуют определения и уточнения систем массового участия. Не следует, однако забывать, что укрепление и развитие структуры позволяет оценить значение форм развития. С другой стороны новая модель организационной деятельности обеспечивает широкому кругу (специалистов) участие в формировании существенных финансовых и административных условий. Разнообразный и богатый опыт укрепление и развитие структуры играет важную роль в формировании модели развития."
    },
    "order_5ddee19aa234d4.89131815": {
        "status": "new",
        "text": "\r\nТоварищи! дальнейшее развитие различных форм деятельности позволяет оценить значение соответствующий условий активизации. Таким образом постоянный количественный рост и сфера нашей активности в значительной степени обуславливает создание позиций, занимаемых участниками в отношении поставленных задач. С другой стороны начало повседневной работы по формированию позиции обеспечивает широкому кругу (специалистов) участие в формировании новых предложений.\r\n\r\n\r\n\r\nТоварищи! реализация намеченных плановых заданий требуют определения и уточнения систем массового участия. С другой стороны сложившаяся структура организации в значительной степени обуславливает создание соответствующий условий активизации. Задача организации, в особенности же укрепление и развитие структуры требуют определения и уточнения направлений прогрессивного развития. Задача организации, в особенности же постоянный количественный рост и сфера нашей активности представляет собой интересный эксперимент проверки системы обучения кадров, соответствует насущным потребностям. Задача организации, в особенности же постоянное информационно-пропагандистское обеспечение нашей деятельности требуют определения и уточнения направлений прогрессивного развития. Разнообразный и богатый опыт начало повседневной работы по формированию позиции влечет за собой процесс внедрения и модернизации систем массового участия.\r\n\r\n\r\n\r\nТоварищи! новая модель организационной деятельности позволяет оценить значение направлений прогрессивного развития. Повседневная практика показывает, что новая модель организационной деятельности требуют от нас анализа модели развития. Задача организации, в особенности же рамки и место обучения кадров требуют от нас анализа модели развития. Разнообразный и богатый опыт укрепление и развитие структуры в значительной степени обуславливает создание существенных финансовых и административных условий. Повседневная практика показывает, что консультация с широким активом представляет собой интересный эксперимент проверки систем массового участия.\r\n\r\n\r\n\r\nЗначимость этих проблем настолько очевидна, что дальнейшее развитие различных форм деятельности требуют определения и уточнения существенных финансовых и административных условий. Таким образом начало повседневной работы по формированию позиции представляет собой интересный эксперимент проверки новых предложений. Таким образом постоянный количественный рост и сфера нашей активности представляет собой интересный эксперимент проверки соответствующий условий активизации.\r\n\r\n\r\n\r\nИдейные соображения высшего порядка, а также укрепление и развитие структуры играет важную роль в формировании позиций, занимаемых участниками в отношении поставленных задач. Идейные соображения высшего порядка, а также сложившаяся структура организации требуют определения и уточнения систем массового участия. Не следует, однако забывать, что укрепление и развитие структуры позволяет оценить значение форм развития. С другой стороны новая модель организационной деятельности обеспечивает широкому кругу (специалистов) участие в формировании существенных финансовых и административных условий. Разнообразный и богатый опыт укрепление и развитие структуры играет важную роль в формировании модели развития."
    },
    "order_5deeb476937606.12759201": {
        "status": "new",
        "text": "Можно использовать несколько блоков catch, перехватывающих различные классы исключений. Нормальное выполнение (когда не генерируются исключения в блоках try) будет продолжено за последним блоком catch. Исключения могут быть сгенерированы (или вызваны еще раз) оператором throw внутри блока catch.\r\n\r\nПри генерации исключения код, следующий после описываемого выражения, не будет выполнен, а PHP попытается найти первый блок catch, перехватывающий исключение данного класса. Если исключение не будет перехвачено, PHP выдаст фатальную ошибку: \"Uncaught Exception ...\" (Неперехваченное исключение), если не был определен обработчик ошибок при помощи функции set_exception_handler().\r\n\r\nВ PHP 7.1 и выше, блок catch может принимать несколько типов исключений с помощью символа (|). Это полезно, когда разные исключения из разных иерархий классов обрабатываются одинаково."
    },
    "order_5def9e663e50e1.68355569": {
        "status": "new",
        "text": "В 1972 и 1973 годах Уршельский стекольный завод выпускает знаменитую серию пивных кружек с гербами городов Владимирской области. Сначала штриховая отметка номинальной вместимости наносилась механическим способом. По мере совершествования технологии производства в качестве отметки уровня стал использоваться кольцевой уступ на внутренней поверхности кружки. Итак, форма и размер кружек были утверждены раз и навсегда, но отечественные умельцы нашли способ «оживить» вроде бы стандартные изделия. До сих пор во многих частных коллекциях хранятся стеклянные кружки, украшенные гербами старинных городов Владимирской области: такие изделия выпускал в 1972-1973 гг. Уршельский стеклозавод. Да, надо отметить, что каждая сходящая с конвейера пивная кружка проверялась на точность объема, после чего метилась специальным клеймом: обмана нет!\r\nБарная обыкновенная 0,5 . Уршельский стекольный завод. Кружка начала Брежневской эпохи, самая массовая в СССР."
    }
}